grenadine/__init__.py
grenadine/Evaluation/__init__.py
grenadine/Evaluation/evaluation.py
grenadine/Inference/__init__.py
grenadine/Inference/classification_predictors.py
grenadine/Inference/inference.py
grenadine/Inference/regression_predictors.py
grenadine/Inference/statistical_predictors.py
grenadine/Model/__init__.py
grenadine/Model/model.py
grenadine/Preprocessing/__init__.py
grenadine/Preprocessing/discretization.py
grenadine/Preprocessing/rnaseq_normalization.py
grenadine/Preprocessing/scrnaseq_pseudo_bulk.py
grenadine/Preprocessing/standard_preprocessing.py
grenadine/Visualisation/__init__.py
grenadine/Visualisation/goplot.py
grenadine/Visualisation/grnplot.py
grenadine/Visualisation/visualisation.py
grenadine-0.1.17.dist-info/LICENSE
grenadine-0.1.17.dist-info/METADATA
grenadine-0.1.17.dist-info/WHEEL
grenadine-0.1.17.dist-info/top_level.txt
grenadine-0.1.17.dist-info/RECORD
