Metadata-Version: 2.1
Name: grenadine
Version: 0.1.17
Summary: Data-Driven Gene Regulatory Network Inference
Home-page: 
Author: Sergio Peignier, Pauline Schmitt, Matis Zouari, Yann Meunier, Timothée Frouté
Author-email: sergio.peignier@insa-lyon.fr
Classifier: Programming Language :: Python :: 3
Classifier: License :: OSI Approved :: GNU General Public License (GPL)
Classifier: Operating System :: OS Independent
License-File: LICENSE
Requires-Dist: pandas
Requires-Dist: numpy
Requires-Dist: scikit-learn
Requires-Dist: tqdm
Requires-Dist: scipy
Requires-Dist: yellowbrick
Requires-Dist: networkx
